{
  "title": {
    "zh": "中文分类",
    "en": "Category"
  },
  "demos": [
    {
      "filename": "facet1.js",
      "title": {
        "zh": "各国人口出生率",
        "en": "column facet"
      },
      "screenshot": "https://gw.alipayobjects.com/mdn/rms_2274c3/afts/img/A*yRI3QYLprt8AAAAAAAAAAABkARQnAQ"
    },
    {
      "filename": "facet2.js",
      "title": {
        "zh": "各国人口出生率",
        "en": "row facet"
      },
      "screenshot": "https://gw.alipayobjects.com/mdn/rms_2274c3/afts/img/A*hR7HSYWHockAAAAAAAAAAABkARQnAQ"
    },
    {
      "filename": "facet3.js",
      "title": {
        "zh": "2016 年全球十大转基因作物种植面积和耕地总面积对比",
        "en": "row facet"
      },
      "screenshot": "https://gw.alipayobjects.com/mdn/rms_2274c3/afts/img/A*CcFlQ7se_sAAAAAAAAAAAABkARQnAQ"
    }
  ]
}
