{
  "1949": [
    { "value": 0, "city": "河北" },
    { "value": 0, "city": "北京" },
    { "value": 102, "city": "天津" },
    { "value": 0, "city": "山西" },
    { "value": 0, "city": "内蒙古" },
    { "value": 0, "city": "辽宁" },
    { "value": 0, "city": "吉林" },
    { "value": 0, "city": "黑龙江" },
    { "value": 274, "city": "上海" },
    { "value": 0, "city": "江苏" },
    { "value": 0, "city": "浙江" },
    { "value": 0, "city": "安徽" },
    { "value": 0, "city": "福建" },
    { "value": 69, "city": "江西" },
    { "value": 0, "city": "山东" },
    { "value": 0, "city": "河南" },
    { "value": 0, "city": "湖北" },
    { "value": 0, "city": "湖南" },
    { "value": 73, "city": "广东" },
    { "value": 0, "city": "广西" },
    { "value": 0, "city": "海南" },
    { "value": 87, "city": "重庆" },
    { "value": 0, "city": "四川" },
    { "value": 44, "city": "贵州" },
    { "value": 56, "city": "云南" },
    { "value": 0, "city": "西藏" },
    { "value": 0, "city": "陕西" },
    { "value": 0, "city": "甘肃" },
    { "value": 83, "city": "青海" },
    { "value": 0, "city": "宁夏" },
    { "value": 0, "city": "新疆" }
  ],
  "1950": [
    { "value": 0, "city": "河北" },
    { "value": 0, "city": "北京" },
    { "value": 188, "city": "天津" },
    { "value": 0, "city": "山西" },
    { "value": 0, "city": "内蒙古" },
    { "value": 0, "city": "辽宁" },
    { "value": 0, "city": "吉林" },
    { "value": 0, "city": "黑龙江" },
    { "value": 309, "city": "上海" },
    { "value": 0, "city": "江苏" },
    { "value": 83, "city": "浙江" },
    { "value": 0, "city": "安徽" },
    { "value": 79, "city": "福建" },
    { "value": 98, "city": "江西" },
    { "value": 0, "city": "山东" },
    { "value": 0, "city": "河南" },
    { "value": 0, "city": "湖北" },
    { "value": 0, "city": "湖南" },
    { "value": 78, "city": "广东" },
    { "value": 0, "city": "广西" },
    { "value": 0, "city": "海南" },
    { "value": 91, "city": "重庆" },
    { "value": 0, "city": "四川" },
    { "value": 45, "city": "贵州" },
    { "value": 59, "city": "云南" },
    { "value": 0, "city": "西藏" },
    { "value": 0, "city": "陕西" },
    { "value": 0, "city": "甘肃" },
    { "value": 88, "city": "青海" },
    { "value": 0, "city": "宁夏" },
    { "value": 0, "city": "新疆" }
  ],
  "1951": [
    { "value": 0, "city": "河北" },
    { "value": 0, "city": "北京" },
    { "value": 278, "city": "天津" },
    { "value": 0, "city": "山西" },
    { "value": 0, "city": "内蒙古" },
    { "value": 0, "city": "辽宁" },
    { "value": 0, "city": "吉林" },
    { "value": 0, "city": "黑龙江" },
    { "value": 388, "city": "上海" },
    { "value": 0, "city": "江苏" },
    { "value": 98, "city": "浙江" },
    { "value": 0, "city": "安徽" },
    { "value": 0, "city": "福建" },
    { "value": 94, "city": "江西" },
    { "value": 0, "city": "山东" },
    { "value": 0, "city": "河南" },
    { "value": 0, "city": "湖北" },
    { "value": 0, "city": "湖南" },
    { "value": 89, "city": "广东" },
    { "value": 0, "city": "广西" },
    { "value": 0, "city": "海南" },
    { "value": 94, "city": "重庆" },
    { "value": 0, "city": "四川" },
    { "value": 54, "city": "贵州" },
    { "value": 64, "city": "云南" },
    { "value": 114, "city": "西藏" },
    { "value": 0, "city": "陕西" },
    { "value": 0, "city": "甘肃" },
    { "value": 94, "city": "青海" },
    { "value": 0, "city": "宁夏" },
    { "value": 0, "city": "新疆" }
  ],
  "1952": [
    { "value": 125, "city": "河北" },
    { "value": 165, "city": "北京" },
    { "value": 298, "city": "天津" },
    { "value": 116, "city": "山西" },
    { "value": 173, "city": "内蒙古" },
    { "value": 218, "city": "辽宁" },
    { "value": 153, "city": "吉林" },
    { "value": 238, "city": "黑龙江" },
    { "value": 430, "city": "上海" },
    { "value": 131, "city": "江苏" },
    { "value": 112, "city": "浙江" },
    { "value": 78, "city": "安徽" },
    { "value": 102, "city": "福建" },
    { "value": 114, "city": "江西" },
    { "value": 91, "city": "山东" },
    { "value": 82.8, "city": "河南" },
    { "value": 90.1, "city": "湖北" },
    { "value": 86, "city": "湖南" },
    { "value": 101, "city": "广东" },
    { "value": 67, "city": "广西" },
    { "value": 0, "city": "海南" },
    { "value": 102, "city": "重庆" },
    { "value": 53, "city": "四川" },
    { "value": 58, "city": "贵州" },
    { "value": 70, "city": "云南" },
    { "value": 115, "city": "西藏" },
    { "value": 85, "city": "陕西" },
    { "value": 125, "city": "甘肃" },
    { "value": 101, "city": "青海" },
    { "value": 126, "city": "宁夏" },
    { "value": 166, "city": "新疆" }
  ],
  "1953": [
    { "value": 128, "city": "河北" },
    { "value": 385, "city": "北京" },
    { "value": 393, "city": "天津" },
    { "value": 141, "city": "山西" },
    { "value": 211, "city": "内蒙古" },
    { "value": 266, "city": "辽宁" },
    { "value": 166, "city": "吉林" },
    { "value": 278, "city": "黑龙江" },
    { "value": 590, "city": "上海" },
    { "value": 141, "city": "江苏" },
    { "value": 122, "city": "浙江" },
    { "value": 89, "city": "安徽" },
    { "value": 112, "city": "福建" },
    { "value": 118, "city": "江西" },
    { "value": 94, "city": "山东" },
    { "value": 93.9, "city": "河南" },
    { "value": 109, "city": "湖北" },
    { "value": 91, "city": "湖南" },
    { "value": 139, "city": "广东" },
    { "value": 73, "city": "广西" },
    { "value": 0, "city": "海南" },
    { "value": 119, "city": "重庆" },
    { "value": 59, "city": "四川" },
    { "value": 66, "city": "贵州" },
    { "value": 87, "city": "云南" },
    { "value": 118, "city": "西藏" },
    { "value": 111, "city": "陕西" },
    { "value": 126, "city": "甘肃" },
    { "value": 106, "city": "青海" },
    { "value": 115, "city": "宁夏" },
    { "value": 179, "city": "新疆" }
  ],
  "1954": [
    { "value": 134, "city": "河北" },
    { "value": 395, "city": "北京" },
    { "value": 362, "city": "天津" },
    { "value": 151, "city": "山西" },
    { "value": 249, "city": "内蒙古" },
    { "value": 272, "city": "辽宁" },
    { "value": 176, "city": "吉林" },
    { "value": 300, "city": "黑龙江" },
    { "value": 589, "city": "上海" },
    { "value": 140, "city": "江苏" },
    { "value": 125, "city": "浙江" },
    { "value": 89, "city": "安徽" },
    { "value": 113, "city": "福建" },
    { "value": 121, "city": "江西" },
    { "value": 106, "city": "山东" },
    { "value": 98, "city": "河南" },
    { "value": 90, "city": "湖北" },
    { "value": 90, "city": "湖南" },
    { "value": 153, "city": "广东" },
    { "value": 81, "city": "广西" },
    { "value": 0, "city": "海南" },
    { "value": 123, "city": "重庆" },
    { "value": 66, "city": "四川" },
    { "value": 72, "city": "贵州" },
    { "value": 97, "city": "云南" },
    { "value": 119, "city": "西藏" },
    { "value": 123, "city": "陕西" },
    { "value": 146, "city": "甘肃" },
    { "value": 138, "city": "青海" },
    { "value": 138, "city": "宁夏" },
    { "value": 211, "city": "新疆" }
  ],
  "1955": [
    { "value": 141, "city": "河北" },
    { "value": 427, "city": "北京" },
    { "value": 356, "city": "天津" },
    { "value": 160, "city": "山西" },
    { "value": 213, "city": "内蒙古" },
    { "value": 272, "city": "辽宁" },
    { "value": 177, "city": "吉林" },
    { "value": 297, "city": "黑龙江" },
    { "value": 569, "city": "上海" },
    { "value": 150, "city": "江苏" },
    { "value": 130, "city": "浙江" },
    { "value": 117, "city": "安徽" },
    { "value": 122, "city": "福建" },
    { "value": 125, "city": "江西" },
    { "value": 113, "city": "山东" },
    { "value": 101, "city": "河南" },
    { "value": 117.9, "city": "湖北" },
    { "value": 104, "city": "湖南" },
    { "value": 152, "city": "广东" },
    { "value": 86, "city": "广西" },
    { "value": 0, "city": "海南" },
    { "value": 123, "city": "重庆" },
    { "value": 74, "city": "四川" },
    { "value": 74, "city": "贵州" },
    { "value": 103, "city": "云南" },
    { "value": 122, "city": "西藏" },
    { "value": 122, "city": "陕西" },
    { "value": 154, "city": "甘肃" },
    { "value": 164, "city": "青海" },
    { "value": 138, "city": "宁夏" },
    { "value": 241, "city": "新疆" }
  ],
  "1956": [
    { "value": 140, "city": "河北" },
    { "value": 454, "city": "北京" },
    { "value": 417, "city": "天津" },
    { "value": 186, "city": "山西" },
    { "value": 283, "city": "内蒙古" },
    { "value": 319, "city": "辽宁" },
    { "value": 200, "city": "吉林" },
    { "value": 308, "city": "黑龙江" },
    { "value": 681, "city": "上海" },
    { "value": 153, "city": "江苏" },
    { "value": 139, "city": "浙江" },
    { "value": 109, "city": "安徽" },
    { "value": 150, "city": "福建" },
    { "value": 124, "city": "江西" },
    { "value": 121, "city": "山东" },
    { "value": 102.5, "city": "河南" },
    { "value": 152, "city": "湖北" },
    { "value": 109, "city": "湖南" },
    { "value": 166, "city": "广东" },
    { "value": 94, "city": "广西" },
    { "value": 0, "city": "海南" },
    { "value": 133, "city": "重庆" },
    { "value": 88, "city": "四川" },
    { "value": 91, "city": "贵州" },
    { "value": 117, "city": "云南" },
    { "value": 137, "city": "西藏" },
    { "value": 156, "city": "陕西" },
    { "value": 174, "city": "甘肃" },
    { "value": 199, "city": "青海" },
    { "value": 152, "city": "宁夏" },
    { "value": 268, "city": "新疆" }
  ],
  "1957": [
    { "value": 144, "city": "河北" },
    { "value": 525, "city": "北京" },
    { "value": 465, "city": "天津" },
    { "value": 186, "city": "山西" },
    { "value": 232, "city": "内蒙古" },
    { "value": 335, "city": "辽宁" },
    { "value": 202, "city": "吉林" },
    { "value": 307, "city": "黑龙江" },
    { "value": 713, "city": "上海" },
    { "value": 157, "city": "江苏" },
    { "value": 151, "city": "浙江" },
    { "value": 126, "city": "安徽" },
    { "value": 154, "city": "福建" },
    { "value": 152, "city": "江西" },
    { "value": 116, "city": "山东" },
    { "value": 109.8, "city": "河南" },
    { "value": 162.2, "city": "湖北" },
    { "value": 127, "city": "湖南" },
    { "value": 179, "city": "广东" },
    { "value": 102, "city": "广西" },
    { "value": 0, "city": "海南" },
    { "value": 129, "city": "重庆" },
    { "value": 103, "city": "四川" },
    { "value": 99, "city": "贵州" },
    { "value": 121, "city": "云南" },
    { "value": 131, "city": "西藏" },
    { "value": 144, "city": "陕西" },
    { "value": 160, "city": "甘肃" },
    { "value": 193, "city": "青海" },
    { "value": 147, "city": "宁夏" },
    { "value": 267, "city": "新疆" }
  ],
  "1958": [
    { "value": 172, "city": "河北" },
    { "value": 534, "city": "北京" },
    { "value": 600, "city": "天津" },
    { "value": 246, "city": "山西" },
    { "value": 292, "city": "内蒙古" },
    { "value": 437, "city": "辽宁" },
    { "value": 243, "city": "吉林" },
    { "value": 405, "city": "黑龙江" },
    { "value": 952, "city": "上海" },
    { "value": 178, "city": "江苏" },
    { "value": 173, "city": "浙江" },
    { "value": 152, "city": "安徽" },
    { "value": 166, "city": "福建" },
    { "value": 166, "city": "江西" },
    { "value": 135, "city": "山东" },
    { "value": 124.2, "city": "河南" },
    { "value": 198, "city": "湖北" },
    { "value": 154, "city": "湖南" },
    { "value": 200, "city": "广东" },
    { "value": 113, "city": "广西" },
    { "value": 0, "city": "海南" },
    { "value": 167, "city": "重庆" },
    { "value": 124, "city": "四川" },
    { "value": 120, "city": "贵州" },
    { "value": 122, "city": "云南" },
    { "value": 143, "city": "西藏" },
    { "value": 171, "city": "陕西" },
    { "value": 178, "city": "甘肃" },
    { "value": 225, "city": "青海" },
    { "value": 176, "city": "宁夏" },
    { "value": 294, "city": "新疆" }
  ],
  "1959": [
    { "value": 197, "city": "河北" },
    { "value": 678, "city": "北京" },
    { "value": 735, "city": "天津" },
    { "value": 294, "city": "山西" },
    { "value": 349, "city": "内蒙古" },
    { "value": 553, "city": "辽宁" },
    { "value": 280, "city": "吉林" },
    { "value": 453, "city": "黑龙江" },
    { "value": 1268, "city": "上海" },
    { "value": 186, "city": "江苏" },
    { "value": 183, "city": "浙江" },
    { "value": 170, "city": "安徽" },
    { "value": 192, "city": "福建" },
    { "value": 178, "city": "江西" },
    { "value": 141, "city": "山东" },
    { "value": 129.1, "city": "河南" },
    { "value": 203, "city": "湖北" },
    { "value": 168, "city": "湖南" },
    { "value": 215, "city": "广东" },
    { "value": 122, "city": "广西" },
    { "value": 0, "city": "海南" },
    { "value": 181, "city": "重庆" },
    { "value": 115, "city": "四川" },
    { "value": 136, "city": "贵州" },
    { "value": 133, "city": "云南" },
    { "value": 142, "city": "西藏" },
    { "value": 192, "city": "陕西" },
    { "value": 183, "city": "甘肃" },
    { "value": 284, "city": "青海" },
    { "value": 217, "city": "宁夏" },
    { "value": 344, "city": "新疆" }
  ],
  "1960": [
    { "value": 194, "city": "河北" },
    { "value": 795, "city": "北京" },
    { "value": 736, "city": "天津" },
    { "value": 298, "city": "山西" },
    { "value": 325, "city": "内蒙古" },
    { "value": 625, "city": "辽宁" },
    { "value": 289, "city": "吉林" },
    { "value": 461, "city": "黑龙江" },
    { "value": 1521, "city": "上海" },
    { "value": 203, "city": "江苏" },
    { "value": 181, "city": "浙江" },
    { "value": 185, "city": "安徽" },
    { "value": 190, "city": "福建" },
    { "value": 185, "city": "江西" },
    { "value": 135, "city": "山东" },
    { "value": 135.1, "city": "河南" },
    { "value": 201, "city": "湖北" },
    { "value": 176, "city": "湖南" },
    { "value": 210, "city": "广东" },
    { "value": 119, "city": "广西" },
    { "value": 0, "city": "海南" },
    { "value": 188, "city": "重庆" },
    { "value": 86, "city": "四川" },
    { "value": 135, "city": "贵州" },
    { "value": 134, "city": "云南" },
    { "value": 204, "city": "西藏" },
    { "value": 200, "city": "陕西" },
    { "value": 143, "city": "甘肃" },
    { "value": 300, "city": "青海" },
    { "value": 227, "city": "宁夏" },
    { "value": 374, "city": "新疆" }
  ],
  "1961": [
    { "value": 145, "city": "河北" },
    { "value": 498, "city": "北京" },
    { "value": 482, "city": "天津" },
    { "value": 200, "city": "山西" },
    { "value": 215, "city": "内蒙古" },
    { "value": 299, "city": "辽宁" },
    { "value": 213, "city": "吉林" },
    { "value": 292, "city": "黑龙江" },
    { "value": 966, "city": "上海" },
    { "value": 170, "city": "江苏" },
    { "value": 154, "city": "浙江" },
    { "value": 145, "city": "安徽" },
    { "value": 147, "city": "福建" },
    { "value": 176, "city": "江西" },
    { "value": 121, "city": "山东" },
    { "value": 96.2, "city": "河南" },
    { "value": 154, "city": "湖北" },
    { "value": 132, "city": "湖南" },
    { "value": 178, "city": "广东" },
    { "value": 110, "city": "广西" },
    { "value": 0, "city": "海南" },
    { "value": 150, "city": "重庆" },
    { "value": 97, "city": "四川" },
    { "value": 110, "city": "贵州" },
    { "value": 121, "city": "云南" },
    { "value": 189, "city": "西藏" },
    { "value": 162, "city": "陕西" },
    { "value": 97, "city": "甘肃" },
    { "value": 233, "city": "青海" },
    { "value": 199, "city": "宁夏" },
    { "value": 305, "city": "新疆" }
  ],
  "1962": [
    { "value": 127, "city": "河北" },
    { "value": 405, "city": "北京" },
    { "value": 406, "city": "天津" },
    { "value": 188, "city": "山西" },
    { "value": 215, "city": "内蒙古" },
    { "value": 292, "city": "辽宁" },
    { "value": 210, "city": "吉林" },
    { "value": 288, "city": "黑龙江" },
    { "value": 803, "city": "上海" },
    { "value": 161, "city": "江苏" },
    { "value": 163, "city": "浙江" },
    { "value": 129, "city": "安徽" },
    { "value": 137, "city": "福建" },
    { "value": 163, "city": "江西" },
    { "value": 120, "city": "山东" },
    { "value": 88.3, "city": "河南" },
    { "value": 161.5, "city": "湖北" },
    { "value": 144, "city": "湖南" },
    { "value": 204, "city": "广东" },
    { "value": 109, "city": "广西" },
    { "value": 0, "city": "海南" },
    { "value": 135, "city": "重庆" },
    { "value": 106, "city": "四川" },
    { "value": 100, "city": "贵州" },
    { "value": 127, "city": "云南" },
    { "value": 188, "city": "西藏" },
    { "value": 135, "city": "陕西" },
    { "value": 101, "city": "甘肃" },
    { "value": 218, "city": "青海" },
    { "value": 200, "city": "宁夏" },
    { "value": 249, "city": "新疆" }
  ],
  "1963": [
    { "value": 114, "city": "河北" },
    { "value": 426, "city": "北京" },
    { "value": 433, "city": "天津" },
    { "value": 191, "city": "山西" },
    { "value": 243, "city": "内蒙古" },
    { "value": 293, "city": "辽宁" },
    { "value": 235, "city": "吉林" },
    { "value": 320, "city": "黑龙江" },
    { "value": 851, "city": "上海" },
    { "value": 172, "city": "江苏" },
    { "value": 169, "city": "浙江" },
    { "value": 128, "city": "安徽" },
    { "value": 142, "city": "福建" },
    { "value": 158, "city": "江西" },
    { "value": 123, "city": "山东" },
    { "value": 85.4, "city": "河南" },
    { "value": 170, "city": "湖北" },
    { "value": 131, "city": "湖南" },
    { "value": 225, "city": "广东" },
    { "value": 108, "city": "广西" },
    { "value": 0, "city": "海南" },
    { "value": 146, "city": "重庆" },
    { "value": 110, "city": "四川" },
    { "value": 100, "city": "贵州" },
    { "value": 129, "city": "云南" },
    { "value": 196, "city": "西藏" },
    { "value": 135, "city": "陕西" },
    { "value": 130, "city": "甘肃" },
    { "value": 232, "city": "青海" },
    { "value": 195, "city": "宁夏" },
    { "value": 267, "city": "新疆" }
  ],
  "1964": [
    { "value": 143, "city": "河北" },
    { "value": 469, "city": "北京" },
    { "value": 483, "city": "天津" },
    { "value": 213, "city": "山西" },
    { "value": 262, "city": "内蒙古" },
    { "value": 324, "city": "辽宁" },
    { "value": 246, "city": "吉林" },
    { "value": 339, "city": "黑龙江" },
    { "value": 933, "city": "上海" },
    { "value": 200, "city": "江苏" },
    { "value": 182, "city": "浙江" },
    { "value": 140, "city": "安徽" },
    { "value": 153, "city": "福建" },
    { "value": 166, "city": "江西" },
    { "value": 128, "city": "山东" },
    { "value": 101.4, "city": "河南" },
    { "value": 182, "city": "湖北" },
    { "value": 153, "city": "湖南" },
    { "value": 219, "city": "广东" },
    { "value": 117, "city": "广西" },
    { "value": 0, "city": "海南" },
    { "value": 164, "city": "重庆" },
    { "value": 117, "city": "四川" },
    { "value": 114, "city": "贵州" },
    { "value": 142, "city": "云南" },
    { "value": 212, "city": "西藏" },
    { "value": 141, "city": "陕西" },
    { "value": 152, "city": "甘肃" },
    { "value": 257, "city": "青海" },
    { "value": 194, "city": "宁夏" },
    { "value": 292, "city": "新疆" }
  ],
  "1965": [
    { "value": 180, "city": "河北" },
    { "value": 509, "city": "北京" },
    { "value": 560, "city": "天津" },
    { "value": 238, "city": "山西" },
    { "value": 275, "city": "内蒙古" },
    { "value": 372, "city": "辽宁" },
    { "value": 262, "city": "吉林" },
    { "value": 377, "city": "黑龙江" },
    { "value": 1042, "city": "上海" },
    { "value": 208, "city": "江苏" },
    { "value": 191, "city": "浙江" },
    { "value": 163, "city": "安徽" },
    { "value": 166, "city": "福建" },
    { "value": 197, "city": "江西" },
    { "value": 152, "city": "山东" },
    { "value": 121.8, "city": "河南" },
    { "value": 209, "city": "湖北" },
    { "value": 170, "city": "湖南" },
    { "value": 227, "city": "广东" },
    { "value": 131, "city": "广西" },
    { "value": 0, "city": "海南" },
    { "value": 184, "city": "重庆" },
    { "value": 130, "city": "四川" },
    { "value": 136, "city": "贵州" },
    { "value": 158, "city": "云南" },
    { "value": 241, "city": "西藏" },
    { "value": 169, "city": "陕西" },
    { "value": 186, "city": "甘肃" },
    { "value": 271, "city": "青海" },
    { "value": 211, "city": "宁夏" },
    { "value": 312, "city": "新疆" }
  ],
  "1966": [
    { "value": 194, "city": "河北" },
    { "value": 566, "city": "北京" },
    { "value": 605, "city": "天津" },
    { "value": 263, "city": "山西" },
    { "value": 289, "city": "内蒙古" },
    { "value": 397, "city": "辽宁" },
    { "value": 277, "city": "吉林" },
    { "value": 426, "city": "黑龙江" },
    { "value": 1140, "city": "上海" },
    { "value": 235, "city": "江苏" },
    { "value": 195, "city": "浙江" },
    { "value": 179, "city": "安徽" },
    { "value": 180, "city": "福建" },
    { "value": 215, "city": "江西" },
    { "value": 169, "city": "山东" },
    { "value": 143.8, "city": "河南" },
    { "value": 236, "city": "湖北" },
    { "value": 184, "city": "湖南" },
    { "value": 245, "city": "广东" },
    { "value": 127, "city": "广西" },
    { "value": 0, "city": "海南" },
    { "value": 184, "city": "重庆" },
    { "value": 137, "city": "四川" },
    { "value": 134, "city": "贵州" },
    { "value": 166, "city": "云南" },
    { "value": 255, "city": "西藏" },
    { "value": 187, "city": "陕西" },
    { "value": 174, "city": "甘肃" },
    { "value": 270, "city": "青海" },
    { "value": 234, "city": "宁夏" },
    { "value": 325, "city": "新疆" }
  ],
  "1967": [
    { "value": 185, "city": "河北" },
    { "value": 480, "city": "北京" },
    { "value": 514, "city": "天津" },
    { "value": 233, "city": "山西" },
    { "value": 233, "city": "内蒙古" },
    { "value": 323, "city": "辽宁" },
    { "value": 257, "city": "吉林" },
    { "value": 409, "city": "黑龙江" },
    { "value": 999, "city": "上海" },
    { "value": 206, "city": "江苏" },
    { "value": 184, "city": "浙江" },
    { "value": 164, "city": "安徽" },
    { "value": 159, "city": "福建" },
    { "value": 192, "city": "江西" },
    { "value": 168, "city": "山东" },
    { "value": 144.2, "city": "河南" },
    { "value": 216, "city": "湖北" },
    { "value": 181, "city": "湖南" },
    { "value": 238, "city": "广东" },
    { "value": 122, "city": "广西" },
    { "value": 0, "city": "海南" },
    { "value": 158, "city": "重庆" },
    { "value": 137, "city": "四川" },
    { "value": 125, "city": "贵州" },
    { "value": 151, "city": "云南" },
    { "value": 268, "city": "西藏" },
    { "value": 166, "city": "陕西" },
    { "value": 160, "city": "甘肃" },
    { "value": 281, "city": "青海" },
    { "value": 228, "city": "宁夏" },
    { "value": 259, "city": "新疆" }
  ],
  "1968": [
    { "value": 185, "city": "河北" },
    { "value": 475, "city": "北京" },
    { "value": 523, "city": "天津" },
    { "value": 187, "city": "山西" },
    { "value": 235, "city": "内蒙古" },
    { "value": 295, "city": "辽宁" },
    { "value": 240, "city": "吉林" },
    { "value": 386, "city": "黑龙江" },
    { "value": 1113, "city": "上海" },
    { "value": 209, "city": "江苏" },
    { "value": 175, "city": "浙江" },
    { "value": 157, "city": "安徽" },
    { "value": 138, "city": "福建" },
    { "value": 193, "city": "江西" },
    { "value": 165, "city": "山东" },
    { "value": 129.2, "city": "河南" },
    { "value": 195, "city": "湖北" },
    { "value": 181, "city": "湖南" },
    { "value": 211, "city": "广东" },
    { "value": 109, "city": "广西" },
    { "value": 0, "city": "海南" },
    { "value": 126, "city": "重庆" },
    { "value": 130, "city": "四川" },
    { "value": 108, "city": "贵州" },
    { "value": 114, "city": "云南" },
    { "value": 246, "city": "西藏" },
    { "value": 124, "city": "陕西" },
    { "value": 157, "city": "甘肃" },
    { "value": 246, "city": "青海" },
    { "value": 202, "city": "宁夏" },
    { "value": 219, "city": "新疆" }
  ],
  "1969": [
    { "value": 210, "city": "河北" },
    { "value": 643, "city": "北京" },
    { "value": 649, "city": "天津" },
    { "value": 224, "city": "山西" },
    { "value": 227, "city": "内蒙古" },
    { "value": 378, "city": "辽宁" },
    { "value": 250, "city": "吉林" },
    { "value": 422, "city": "黑龙江" },
    { "value": 1292, "city": "上海" },
    { "value": 221, "city": "江苏" },
    { "value": 195, "city": "浙江" },
    { "value": 157, "city": "安徽" },
    { "value": 160, "city": "福建" },
    { "value": 211, "city": "江西" },
    { "value": 175, "city": "山东" },
    { "value": 140.4, "city": "河南" },
    { "value": 197, "city": "湖北" },
    { "value": 189, "city": "湖南" },
    { "value": 232, "city": "广东" },
    { "value": 131, "city": "广西" },
    { "value": 0, "city": "海南" },
    { "value": 141, "city": "重庆" },
    { "value": 138, "city": "四川" },
    { "value": 102, "city": "贵州" },
    { "value": 144, "city": "云南" },
    { "value": 237, "city": "西藏" },
    { "value": 175, "city": "陕西" },
    { "value": 178, "city": "甘肃" },
    { "value": 262, "city": "青海" },
    { "value": 225, "city": "宁夏" },
    { "value": 211, "city": "新疆" }
  ],
  "1970": [
    { "value": 232, "city": "河北" },
    { "value": 810, "city": "北京" },
    { "value": 781, "city": "天津" },
    { "value": 277, "city": "山西" },
    { "value": 263, "city": "内蒙古" },
    { "value": 447, "city": "辽宁" },
    { "value": 303, "city": "吉林" },
    { "value": 448, "city": "黑龙江" },
    { "value": 1446, "city": "上海" },
    { "value": 249, "city": "江苏" },
    { "value": 211, "city": "浙江" },
    { "value": 186, "city": "安徽" },
    { "value": 173, "city": "福建" },
    { "value": 229, "city": "江西" },
    { "value": 199, "city": "山东" },
    { "value": 163.5, "city": "河南" },
    { "value": 245, "city": "湖北" },
    { "value": 211, "city": "湖南" },
    { "value": 258, "city": "广东" },
    { "value": 142, "city": "广西" },
    { "value": 0, "city": "海南" },
    { "value": 164, "city": "重庆" },
    { "value": 146, "city": "四川" },
    { "value": 132, "city": "贵州" },
    { "value": 156, "city": "云南" },
    { "value": 247, "city": "西藏" },
    { "value": 196, "city": "陕西" },
    { "value": 218, "city": "甘肃" },
    { "value": 303, "city": "青海" },
    { "value": 241, "city": "宁夏" },
    { "value": 236, "city": "新疆" }
  ],
  "1971": [
    { "value": 234, "city": "河北" },
    { "value": 773, "city": "北京" },
    { "value": 832, "city": "天津" },
    { "value": 290, "city": "山西" },
    { "value": 271, "city": "内蒙古" },
    { "value": 478, "city": "辽宁" },
    { "value": 319, "city": "吉林" },
    { "value": 449, "city": "黑龙江" },
    { "value": 1541, "city": "上海" },
    { "value": 279, "city": "江苏" },
    { "value": 210, "city": "浙江" },
    { "value": 200, "city": "安徽" },
    { "value": 198, "city": "福建" },
    { "value": 238, "city": "江西" },
    { "value": 215, "city": "山东" },
    { "value": 171.5, "city": "河南" },
    { "value": 246, "city": "湖北" },
    { "value": 218, "city": "湖南" },
    { "value": 254, "city": "广东" },
    { "value": 160, "city": "广西" },
    { "value": 0, "city": "海南" },
    { "value": 183, "city": "重庆" },
    { "value": 152, "city": "四川" },
    { "value": 145, "city": "贵州" },
    { "value": 171, "city": "云南" },
    { "value": 262, "city": "西藏" },
    { "value": 234, "city": "陕西" },
    { "value": 231, "city": "甘肃" },
    { "value": 320, "city": "青海" },
    { "value": 288, "city": "宁夏" },
    { "value": 258, "city": "新疆" }
  ],
  "1972": [
    { "value": 220, "city": "河北" },
    { "value": 836, "city": "北京" },
    { "value": 832, "city": "天津" },
    { "value": 282, "city": "山西" },
    { "value": 247, "city": "内蒙古" },
    { "value": 489, "city": "辽宁" },
    { "value": 286, "city": "吉林" },
    { "value": 433, "city": "黑龙江" },
    { "value": 1605, "city": "上海" },
    { "value": 291, "city": "江苏" },
    { "value": 247, "city": "浙江" },
    { "value": 208, "city": "安徽" },
    { "value": 208, "city": "福建" },
    { "value": 248, "city": "江西" },
    { "value": 221, "city": "山东" },
    { "value": 177.7, "city": "河南" },
    { "value": 266, "city": "湖北" },
    { "value": 230, "city": "湖南" },
    { "value": 260, "city": "广东" },
    { "value": 182, "city": "广西" },
    { "value": 0, "city": "海南" },
    { "value": 176, "city": "重庆" },
    { "value": 152, "city": "四川" },
    { "value": 129, "city": "贵州" },
    { "value": 188, "city": "云南" },
    { "value": 270, "city": "西藏" },
    { "value": 229, "city": "陕西" },
    { "value": 243, "city": "甘肃" },
    { "value": 341, "city": "青海" },
    { "value": 302, "city": "宁夏" },
    { "value": 232, "city": "新疆" }
  ],
  "1973": [
    { "value": 236, "city": "河北" },
    { "value": 893, "city": "北京" },
    { "value": 875, "city": "天津" },
    { "value": 296, "city": "山西" },
    { "value": 269, "city": "内蒙古" },
    { "value": 538, "city": "辽宁" },
    { "value": 316, "city": "吉林" },
    { "value": 446, "city": "黑龙江" },
    { "value": 1737, "city": "上海" },
    { "value": 312, "city": "江苏" },
    { "value": 250, "city": "浙江" },
    { "value": 216, "city": "安徽" },
    { "value": 200, "city": "福建" },
    { "value": 242, "city": "江西" },
    { "value": 229, "city": "山东" },
    { "value": 182, "city": "河南" },
    { "value": 248, "city": "湖北" },
    { "value": 244, "city": "湖南" },
    { "value": 277, "city": "广东" },
    { "value": 194, "city": "广西" },
    { "value": 0, "city": "海南" },
    { "value": 174, "city": "重庆" },
    { "value": 156, "city": "四川" },
    { "value": 119, "city": "贵州" },
    { "value": 202, "city": "云南" },
    { "value": 286, "city": "西藏" },
    { "value": 231, "city": "陕西" },
    { "value": 252, "city": "甘肃" },
    { "value": 352, "city": "青海" },
    { "value": 296, "city": "宁夏" },
    { "value": 226, "city": "新疆" }
  ],
  "1974": [
    { "value": 251, "city": "河北" },
    { "value": 965, "city": "北京" },
    { "value": 960, "city": "天津" },
    { "value": 283, "city": "山西" },
    { "value": 256, "city": "内蒙古" },
    { "value": 572, "city": "辽宁" },
    { "value": 319, "city": "吉林" },
    { "value": 460, "city": "黑龙江" },
    { "value": 1805, "city": "上海" },
    { "value": 311, "city": "江苏" },
    { "value": 245, "city": "浙江" },
    { "value": 210, "city": "安徽" },
    { "value": 202, "city": "福建" },
    { "value": 227, "city": "江西" },
    { "value": 191, "city": "山东" },
    { "value": 182.2, "city": "河南" },
    { "value": 274, "city": "湖北" },
    { "value": 223, "city": "湖南" },
    { "value": 291, "city": "广东" },
    { "value": 201, "city": "广西" },
    { "value": 0, "city": "海南" },
    { "value": 168, "city": "重庆" },
    { "value": 160, "city": "四川" },
    { "value": 101, "city": "贵州" },
    { "value": 186, "city": "云南" },
    { "value": 297, "city": "西藏" },
    { "value": 236, "city": "陕西" },
    { "value": 279, "city": "甘肃" },
    { "value": 361, "city": "青海" },
    { "value": 365, "city": "宁夏" },
    { "value": 222, "city": "新疆" }
  ],
  "1975": [
    { "value": 272, "city": "河北" },
    { "value": 1086, "city": "北京" },
    { "value": 991, "city": "天津" },
    { "value": 301, "city": "山西" },
    { "value": 280, "city": "内蒙古" },
    { "value": 607, "city": "辽宁" },
    { "value": 350, "city": "吉林" },
    { "value": 484, "city": "黑龙江" },
    { "value": 1898, "city": "上海" },
    { "value": 329, "city": "江苏" },
    { "value": 235, "city": "浙江" },
    { "value": 218, "city": "安徽" },
    { "value": 203, "city": "福建" },
    { "value": 233, "city": "江西" },
    { "value": 240, "city": "山东" },
    { "value": 190.6, "city": "河南" },
    { "value": 274.3, "city": "湖北" },
    { "value": 239, "city": "湖南" },
    { "value": 326, "city": "广东" },
    { "value": 212, "city": "广西" },
    { "value": 0, "city": "海南" },
    { "value": 190, "city": "重庆" },
    { "value": 169, "city": "四川" },
    { "value": 124, "city": "贵州" },
    { "value": 190, "city": "云南" },
    { "value": 307, "city": "西藏" },
    { "value": 243, "city": "陕西" },
    { "value": 318, "city": "甘肃" },
    { "value": 371, "city": "青海" },
    { "value": 374, "city": "宁夏" },
    { "value": 240, "city": "新疆" }
  ],
  "1976": [
    { "value": 272, "city": "河北" },
    { "value": 1111, "city": "北京" },
    { "value": 908, "city": "天津" },
    { "value": 274, "city": "山西" },
    { "value": 272, "city": "内蒙古" },
    { "value": 619, "city": "辽宁" },
    { "value": 321, "city": "吉林" },
    { "value": 482, "city": "黑龙江" },
    { "value": 1929, "city": "上海" },
    { "value": 332, "city": "江苏" },
    { "value": 240, "city": "浙江" },
    { "value": 234, "city": "安徽" },
    { "value": 201, "city": "福建" },
    { "value": 214, "city": "江西" },
    { "value": 242, "city": "山东" },
    { "value": 184.5, "city": "河南" },
    { "value": 258.3, "city": "湖北" },
    { "value": 236, "city": "湖南" },
    { "value": 319, "city": "广东" },
    { "value": 208, "city": "广西" },
    { "value": 0, "city": "海南" },
    { "value": 188, "city": "重庆" },
    { "value": 190, "city": "四川" },
    { "value": 110, "city": "贵州" },
    { "value": 169, "city": "云南" },
    { "value": 317, "city": "西藏" },
    { "value": 233, "city": "陕西" },
    { "value": 309, "city": "甘肃" },
    { "value": 356, "city": "青海" },
    { "value": 333, "city": "宁夏" },
    { "value": 266, "city": "新疆" }
  ],
  "1977": [
    { "value": 318, "city": "河北" },
    { "value": 1162, "city": "北京" },
    { "value": 938, "city": "天津" },
    { "value": 315, "city": "山西" },
    { "value": 287, "city": "内蒙古" },
    { "value": 612, "city": "辽宁" },
    { "value": 343, "city": "吉林" },
    { "value": 511, "city": "黑龙江" },
    { "value": 2125, "city": "上海" },
    { "value": 353, "city": "江苏" },
    { "value": 271, "city": "浙江" },
    { "value": 235, "city": "安徽" },
    { "value": 220, "city": "福建" },
    { "value": 243, "city": "江西" },
    { "value": 293, "city": "山东" },
    { "value": 208.7, "city": "河南" },
    { "value": 291.8, "city": "湖北" },
    { "value": 254, "city": "湖南" },
    { "value": 340, "city": "广东" },
    { "value": 208, "city": "广西" },
    { "value": 0, "city": "海南" },
    { "value": 208, "city": "重庆" },
    { "value": 222, "city": "四川" },
    { "value": 144, "city": "贵州" },
    { "value": 187, "city": "云南" },
    { "value": 334, "city": "西藏" },
    { "value": 256, "city": "陕西" },
    { "value": 318, "city": "甘肃" },
    { "value": 311, "city": "青海" },
    { "value": 354, "city": "宁夏" },
    { "value": 293, "city": "新疆" }
  ],
  "1978": [
    { "value": 364, "city": "河北" },
    { "value": 1257, "city": "北京" },
    { "value": 1133, "city": "天津" },
    { "value": 365, "city": "山西" },
    { "value": 317, "city": "内蒙古" },
    { "value": 680, "city": "辽宁" },
    { "value": 381, "city": "吉林" },
    { "value": 564, "city": "黑龙江" },
    { "value": 2485, "city": "上海" },
    { "value": 430, "city": "江苏" },
    { "value": 331, "city": "浙江" },
    { "value": 244, "city": "安徽" },
    { "value": 273, "city": "福建" },
    { "value": 276, "city": "江西" },
    { "value": 316, "city": "山东" },
    { "value": 232.3, "city": "河南" },
    { "value": 332, "city": "湖北" },
    { "value": 286, "city": "湖南" },
    { "value": 370, "city": "广东" },
    { "value": 225, "city": "广西" },
    { "value": 314, "city": "海南" },
    { "value": 269, "city": "重庆" },
    { "value": 261, "city": "四川" },
    { "value": 175, "city": "贵州" },
    { "value": 226, "city": "云南" },
    { "value": 375, "city": "西藏" },
    { "value": 291, "city": "陕西" },
    { "value": 348, "city": "甘肃" },
    { "value": 428, "city": "青海" },
    { "value": 370, "city": "宁夏" },
    { "value": 313, "city": "新疆" }
  ],
  "1979": [
    { "value": 400, "city": "河北" },
    { "value": 1358, "city": "北京" },
    { "value": 1241, "city": "天津" },
    { "value": 437, "city": "山西" },
    { "value": 343, "city": "内蒙古" },
    { "value": 717, "city": "辽宁" },
    { "value": 417, "city": "吉林" },
    { "value": 594, "city": "黑龙江" },
    { "value": 2556, "city": "上海" },
    { "value": 509, "city": "江苏" },
    { "value": 417, "city": "浙江" },
    { "value": 268, "city": "安徽" },
    { "value": 300, "city": "福建" },
    { "value": 325, "city": "江西" },
    { "value": 350, "city": "山东" },
    { "value": 266.7, "city": "河南" },
    { "value": 409.4, "city": "湖北" },
    { "value": 343, "city": "湖南" },
    { "value": 410, "city": "广东" },
    { "value": 246, "city": "广西" },
    { "value": 327, "city": "海南" },
    { "value": 301, "city": "重庆" },
    { "value": 289, "city": "四川" },
    { "value": 204, "city": "贵州" },
    { "value": 247, "city": "云南" },
    { "value": 404, "city": "西藏" },
    { "value": 336, "city": "陕西" },
    { "value": 359, "city": "甘肃" },
    { "value": 410, "city": "青海" },
    { "value": 399, "city": "宁夏" },
    { "value": 359, "city": "新疆" }
  ],
  "1980": [
    { "value": 427, "city": "河北" },
    { "value": 1544, "city": "北京" },
    { "value": 1357, "city": "天津" },
    { "value": 442, "city": "山西" },
    { "value": 361, "city": "内蒙古" },
    { "value": 811, "city": "辽宁" },
    { "value": 445, "city": "吉林" },
    { "value": 694, "city": "黑龙江" },
    { "value": 2725, "city": "上海" },
    { "value": 541, "city": "江苏" },
    { "value": 471, "city": "浙江" },
    { "value": 291, "city": "安徽" },
    { "value": 348, "city": "福建" },
    { "value": 342, "city": "江西" },
    { "value": 402, "city": "山东" },
    { "value": 316.7, "city": "河南" },
    { "value": 428, "city": "湖北" },
    { "value": 365, "city": "湖南" },
    { "value": 481, "city": "广东" },
    { "value": 278, "city": "广西" },
    { "value": 354, "city": "海南" },
    { "value": 334, "city": "重庆" },
    { "value": 320, "city": "四川" },
    { "value": 219, "city": "贵州" },
    { "value": 267, "city": "云南" },
    { "value": 471, "city": "西藏" },
    { "value": 334, "city": "陕西" },
    { "value": 388, "city": "甘肃" },
    { "value": 473, "city": "青海" },
    { "value": 433, "city": "宁夏" },
    { "value": 410, "city": "新疆" }
  ],
  "1981": [
    { "value": 427, "city": "河北" },
    { "value": 1526, "city": "北京" },
    { "value": 1458, "city": "天津" },
    { "value": 488, "city": "山西" },
    { "value": 407, "city": "内蒙古" },
    { "value": 823, "city": "辽宁" },
    { "value": 496, "city": "吉林" },
    { "value": 709, "city": "黑龙江" },
    { "value": 2800, "city": "上海" },
    { "value": 586, "city": "江苏" },
    { "value": 531, "city": "浙江" },
    { "value": 346, "city": "安徽" },
    { "value": 416, "city": "福建" },
    { "value": 369, "city": "江西" },
    { "value": 472, "city": "山东" },
    { "value": 340.1, "city": "河南" },
    { "value": 466.3, "city": "湖北" },
    { "value": 394, "city": "湖南" },
    { "value": 550, "city": "广东" },
    { "value": 317, "city": "广西" },
    { "value": 399, "city": "海南" },
    { "value": 354, "city": "重庆" },
    { "value": 337, "city": "四川" },
    { "value": 242, "city": "贵州" },
    { "value": 294, "city": "云南" },
    { "value": 560, "city": "西藏" },
    { "value": 356, "city": "陕西" },
    { "value": 367, "city": "甘肃" },
    { "value": 459, "city": "青海" },
    { "value": 460, "city": "宁夏" },
    { "value": 450, "city": "新疆" }
  ],
  "1982": [
    { "value": 474, "city": "河北" },
    { "value": 1671, "city": "北京" },
    { "value": 1469, "city": "天津" },
    { "value": 551, "city": "山西" },
    { "value": 480, "city": "内蒙古" },
    { "value": 884, "city": "辽宁" },
    { "value": 538, "city": "吉林" },
    { "value": 762, "city": "黑龙江" },
    { "value": 2864, "city": "上海" },
    { "value": 645, "city": "江苏" },
    { "value": 599, "city": "浙江" },
    { "value": 375, "city": "安徽" },
    { "value": 457, "city": "福建" },
    { "value": 403, "city": "江西" },
    { "value": 531, "city": "山东" },
    { "value": 353, "city": "河南" },
    { "value": 506.3, "city": "湖北" },
    { "value": 430, "city": "湖南" },
    { "value": 633, "city": "广东" },
    { "value": 354, "city": "广西" },
    { "value": 510, "city": "海南" },
    { "value": 390, "city": "重庆" },
    { "value": 379, "city": "四川" },
    { "value": 278, "city": "贵州" },
    { "value": 339, "city": "云南" },
    { "value": 544, "city": "西藏" },
    { "value": 385, "city": "陕西" },
    { "value": 393, "city": "甘肃" },
    { "value": 513, "city": "青海" },
    { "value": 469, "city": "宁夏" },
    { "value": 488, "city": "新疆" }
  ],
  "1983": [
    { "value": 526, "city": "河北" },
    { "value": 1943, "city": "北京" },
    { "value": 1555, "city": "天津" },
    { "value": 604, "city": "山西" },
    { "value": 535, "city": "内蒙古" },
    { "value": 1012, "city": "辽宁" },
    { "value": 658, "city": "吉林" },
    { "value": 841, "city": "黑龙江" },
    { "value": 2947, "city": "上海" },
    { "value": 716, "city": "江苏" },
    { "value": 650, "city": "浙江" },
    { "value": 428, "city": "安徽" },
    { "value": 487, "city": "福建" },
    { "value": 428, "city": "江西" },
    { "value": 611, "city": "山东" },
    { "value": 432.9, "city": "河南" },
    { "value": 543.3, "city": "湖北" },
    { "value": 470, "city": "湖南" },
    { "value": 675, "city": "广东" },
    { "value": 363, "city": "广西" },
    { "value": 540, "city": "海南" },
    { "value": 428, "city": "重庆" },
    { "value": 425, "city": "四川" },
    { "value": 302, "city": "贵州" },
    { "value": 363, "city": "云南" },
    { "value": 538, "city": "西藏" },
    { "value": 420, "city": "陕西" },
    { "value": 462, "city": "甘肃" },
    { "value": 569, "city": "青海" },
    { "value": 525, "city": "宁夏" },
    { "value": 583, "city": "新疆" }
  ],
  "1984": [
    { "value": 609, "city": "河北" },
    { "value": 2262, "city": "北京" },
    { "value": 1853, "city": "天津" },
    { "value": 756, "city": "山西" },
    { "value": 640, "city": "内蒙古" },
    { "value": 1203, "city": "辽宁" },
    { "value": 760, "city": "吉林" },
    { "value": 959, "city": "黑龙江" },
    { "value": 3232, "city": "上海" },
    { "value": 843, "city": "江苏" },
    { "value": 810, "city": "浙江" },
    { "value": 523, "city": "安徽" },
    { "value": 591, "city": "福建" },
    { "value": 497, "city": "江西" },
    { "value": 765, "city": "山东" },
    { "value": 481.6, "city": "河南" },
    { "value": 671, "city": "湖北" },
    { "value": 519, "city": "湖南" },
    { "value": 827, "city": "广东" },
    { "value": 399, "city": "广西" },
    { "value": 636, "city": "海南" },
    { "value": 502, "city": "重庆" },
    { "value": 487, "city": "四川" },
    { "value": 371, "city": "贵州" },
    { "value": 416, "city": "云南" },
    { "value": 702, "city": "西藏" },
    { "value": 504, "city": "陕西" },
    { "value": 515, "city": "甘肃" },
    { "value": 662, "city": "青海" },
    { "value": 615, "city": "宁夏" },
    { "value": 661, "city": "新疆" }
  ],
  "1985": [
    { "value": 719, "city": "河北" },
    { "value": 2643, "city": "北京" },
    { "value": 2169, "city": "天津" },
    { "value": 838, "city": "山西" },
    { "value": 809, "city": "内蒙古" },
    { "value": 1413, "city": "辽宁" },
    { "value": 868, "city": "吉林" },
    { "value": 1062, "city": "黑龙江" },
    { "value": 3811, "city": "上海" },
    { "value": 1053, "city": "江苏" },
    { "value": 1067, "city": "浙江" },
    { "value": 646, "city": "安徽" },
    { "value": 737, "city": "福建" },
    { "value": 597, "city": "江西" },
    { "value": 887, "city": "山东" },
    { "value": 579.7, "city": "河南" },
    { "value": 800.7, "city": "湖北" },
    { "value": 626, "city": "湖南" },
    { "value": 1026, "city": "广东" },
    { "value": 471, "city": "广西" },
    { "value": 729, "city": "海南" },
    { "value": 577, "city": "重庆" },
    { "value": 570, "city": "四川" },
    { "value": 420, "city": "贵州" },
    { "value": 486, "city": "云南" },
    { "value": 894, "city": "西藏" },
    { "value": 604, "city": "陕西" },
    { "value": 608, "city": "甘肃" },
    { "value": 808, "city": "青海" },
    { "value": 737, "city": "宁夏" },
    { "value": 820, "city": "新疆" }
  ],
  "1986": [
    { "value": 782, "city": "河北" },
    { "value": 2836, "city": "北京" },
    { "value": 2352, "city": "天津" },
    { "value": 890, "city": "山西" },
    { "value": 888, "city": "内蒙古" },
    { "value": 1633, "city": "辽宁" },
    { "value": 977, "city": "吉林" },
    { "value": 1189, "city": "黑龙江" },
    { "value": 3956, "city": "上海" },
    { "value": 1193, "city": "江苏" },
    { "value": 1237, "city": "浙江" },
    { "value": 738, "city": "安徽" },
    { "value": 809, "city": "福建" },
    { "value": 652, "city": "江西" },
    { "value": 956, "city": "山东" },
    { "value": 635.3, "city": "河南" },
    { "value": 881.6, "city": "湖北" },
    { "value": 703, "city": "湖南" },
    { "value": 1164, "city": "广东" },
    { "value": 525, "city": "广西" },
    { "value": 798, "city": "海南" },
    { "value": 640, "city": "重庆" },
    { "value": 614, "city": "四川" },
    { "value": 467, "city": "贵州" },
    { "value": 528, "city": "云南" },
    { "value": 842, "city": "西藏" },
    { "value": 688, "city": "陕西" },
    { "value": 684, "city": "甘肃" },
    { "value": 916, "city": "青海" },
    { "value": 823, "city": "宁夏" },
    { "value": 924, "city": "新疆" }
  ],
  "1987": [
    { "value": 921, "city": "河北" },
    { "value": 3150, "city": "北京" },
    { "value": 2621, "city": "天津" },
    { "value": 962, "city": "山西" },
    { "value": 1025, "city": "内蒙古" },
    { "value": 1917, "city": "辽宁" },
    { "value": 1269, "city": "吉林" },
    { "value": 1335, "city": "黑龙江" },
    { "value": 4340, "city": "上海" },
    { "value": 1462, "city": "江苏" },
    { "value": 1478, "city": "浙江" },
    { "value": 842, "city": "安徽" },
    { "value": 999, "city": "福建" },
    { "value": 729, "city": "江西" },
    { "value": 1131, "city": "山东" },
    { "value": 755.8, "city": "河南" },
    { "value": 1018.4, "city": "湖北" },
    { "value": 818, "city": "湖南" },
    { "value": 1443, "city": "广东" },
    { "value": 607, "city": "广西" },
    { "value": 925.3, "city": "海南" },
    { "value": 705, "city": "重庆" },
    { "value": 702, "city": "四川" },
    { "value": 546, "city": "贵州" },
    { "value": 653, "city": "云南" },
    { "value": 863, "city": "西藏" },
    { "value": 794, "city": "陕西" },
    { "value": 764, "city": "甘肃" },
    { "value": 1018, "city": "青海" },
    { "value": 922, "city": "宁夏" },
    { "value": 1053, "city": "新疆" }
  ],
  "1988": [
    { "value": 1219, "city": "河北" },
    { "value": 3892, "city": "北京" },
    { "value": 3035, "city": "天津" },
    { "value": 1168, "city": "山西" },
    { "value": 1291, "city": "内蒙古" },
    { "value": 2285, "city": "辽宁" },
    { "value": 1559, "city": "吉林" },
    { "value": 1602, "city": "黑龙江" },
    { "value": 5080, "city": "上海" },
    { "value": 1891, "city": "江苏" },
    { "value": 1853, "city": "浙江" },
    { "value": 1026, "city": "安徽" },
    { "value": 1349, "city": "福建" },
    { "value": 891, "city": "江西" },
    { "value": 1395, "city": "山东" },
    { "value": 909.9, "city": "河南" },
    { "value": 1215.9, "city": "湖北" },
    { "value": 999, "city": "湖南" },
    { "value": 1926, "city": "广东" },
    { "value": 770, "city": "广西" },
    { "value": 1220.3, "city": "海南" },
    { "value": 880, "city": "重庆" },
    { "value": 861, "city": "四川" },
    { "value": 683, "city": "贵州" },
    { "value": 845, "city": "云南" },
    { "value": 964, "city": "西藏" },
    { "value": 1004, "city": "陕西" },
    { "value": 905, "city": "甘肃" },
    { "value": 1260, "city": "青海" },
    { "value": 1143, "city": "宁夏" },
    { "value": 1347, "city": "新疆" }
  ],
  "1989": [
    { "value": 1409, "city": "河北" },
    { "value": 4269, "city": "北京" },
    { "value": 3261, "city": "天津" },
    { "value": 1367, "city": "山西" },
    { "value": 1377, "city": "内蒙古" },
    { "value": 2574, "city": "辽宁" },
    { "value": 1636, "city": "吉林" },
    { "value": 1808, "city": "黑龙江" },
    { "value": 5362, "city": "上海" },
    { "value": 2038, "city": "江苏" },
    { "value": 2023, "city": "浙江" },
    { "value": 1136, "city": "安徽" },
    { "value": 1589, "city": "福建" },
    { "value": 1013, "city": "江西" },
    { "value": 1595, "city": "山东" },
    { "value": 1012.3, "city": "河南" },
    { "value": 1373.2, "city": "湖北" },
    { "value": 1074, "city": "湖南" },
    { "value": 2251, "city": "广东" },
    { "value": 927, "city": "广西" },
    { "value": 1420.2, "city": "海南" },
    { "value": 1011, "city": "重庆" },
    { "value": 960, "city": "四川" },
    { "value": 750, "city": "贵州" },
    { "value": 1003, "city": "云南" },
    { "value": 1021, "city": "西藏" },
    { "value": 1124, "city": "陕西" },
    { "value": 1007, "city": "甘肃" },
    { "value": 1365, "city": "青海" },
    { "value": 1317, "city": "宁夏" },
    { "value": 1493, "city": "新疆" }
  ],
  "1990": [
    { "value": 1465, "city": "河北" },
    { "value": 4635, "city": "北京" },
    { "value": 3487, "city": "天津" },
    { "value": 1528, "city": "山西" },
    { "value": 1478, "city": "内蒙古" },
    { "value": 2698, "city": "辽宁" },
    { "value": 1746, "city": "吉林" },
    { "value": 2028, "city": "黑龙江" },
    { "value": 5911, "city": "上海" },
    { "value": 2109, "city": "江苏" },
    { "value": 2138, "city": "浙江" },
    { "value": 1182, "city": "安徽" },
    { "value": 1763, "city": "福建" },
    { "value": 1134, "city": "江西" },
    { "value": 1815, "city": "山东" },
    { "value": 1090.6, "city": "河南" },
    { "value": 1541.2, "city": "湖北" },
    { "value": 1228, "city": "湖南" },
    { "value": 2484, "city": "广东" },
    { "value": 1066, "city": "广西" },
    { "value": 1562.5, "city": "海南" },
    { "value": 1080, "city": "重庆" },
    { "value": 1136, "city": "四川" },
    { "value": 810, "city": "贵州" },
    { "value": 1224, "city": "云南" },
    { "value": 1276, "city": "西藏" },
    { "value": 1241, "city": "陕西" },
    { "value": 1099, "city": "甘肃" },
    { "value": 1558, "city": "青海" },
    { "value": 1393, "city": "宁夏" },
    { "value": 1713, "city": "新疆" }
  ],
  "1991": [
    { "value": 1727, "city": "河北" },
    { "value": 5494, "city": "北京" },
    { "value": 3777, "city": "天津" },
    { "value": 1592, "city": "山西" },
    { "value": 1642, "city": "内蒙古" },
    { "value": 3027, "city": "辽宁" },
    { "value": 1878, "city": "吉林" },
    { "value": 2310, "city": "黑龙江" },
    { "value": 6661, "city": "上海" },
    { "value": 2353, "city": "江苏" },
    { "value": 2558, "city": "浙江" },
    { "value": 1164, "city": "安徽" },
    { "value": 2041, "city": "福建" },
    { "value": 1249, "city": "江西" },
    { "value": 2122, "city": "山东" },
    { "value": 1201.2, "city": "河南" },
    { "value": 1668, "city": "湖北" },
    { "value": 1357, "city": "湖南" },
    { "value": 2941, "city": "广东" },
    { "value": 1211, "city": "广西" },
    { "value": 1804.2, "city": "海南" },
    { "value": 1221, "city": "重庆" },
    { "value": 1283, "city": "四川" },
    { "value": 896, "city": "贵州" },
    { "value": 1377, "city": "云南" },
    { "value": 1358, "city": "西藏" },
    { "value": 1402, "city": "陕西" },
    { "value": 1204, "city": "甘肃" },
    { "value": 1647, "city": "青海" },
    { "value": 1511, "city": "宁夏" },
    { "value": 2101, "city": "新疆" }
  ],
  "1992": [
    { "value": 2040, "city": "河北" },
    { "value": 6458, "city": "北京" },
    { "value": 4481, "city": "天津" },
    { "value": 1862, "city": "山西" },
    { "value": 1906, "city": "内蒙古" },
    { "value": 3693, "city": "辽宁" },
    { "value": 2246, "city": "吉林" },
    { "value": 2672, "city": "黑龙江" },
    { "value": 8208, "city": "上海" },
    { "value": 3106, "city": "江苏" },
    { "value": 3212, "city": "浙江" },
    { "value": 1390, "city": "安徽" },
    { "value": 2557, "city": "福建" },
    { "value": 1472, "city": "江西" },
    { "value": 2556, "city": "山东" },
    { "value": 1452.3, "city": "河南" },
    { "value": 1962.4, "city": "湖北" },
    { "value": 1595, "city": "湖南" },
    { "value": 3699, "city": "广东" },
    { "value": 1490, "city": "广西" },
    { "value": 2719.3, "city": "海南" },
    { "value": 1495, "city": "重庆" },
    { "value": 1477, "city": "四川" },
    { "value": 1034, "city": "贵州" },
    { "value": 1625, "city": "云南" },
    { "value": 1468, "city": "西藏" },
    { "value": 1571, "city": "陕西" },
    { "value": 1384, "city": "甘肃" },
    { "value": 1890, "city": "青海" },
    { "value": 1718, "city": "宁夏" },
    { "value": 2477, "city": "新疆" }
  ],
  "1993": [
    { "value": 2682, "city": "河北" },
    { "value": 8006, "city": "北京" },
    { "value": 5800, "city": "天津" },
    { "value": 2271, "city": "山西" },
    { "value": 2423, "city": "内蒙古" },
    { "value": 5015, "city": "辽宁" },
    { "value": 2826, "city": "吉林" },
    { "value": 3306, "city": "黑龙江" },
    { "value": 11061, "city": "上海" },
    { "value": 4321, "city": "江苏" },
    { "value": 4469, "city": "浙江" },
    { "value": 1785, "city": "安徽" },
    { "value": 3556, "city": "福建" },
    { "value": 1835, "city": "江西" },
    { "value": 3222, "city": "山东" },
    { "value": 1864.6, "city": "河南" },
    { "value": 2360.5, "city": "湖北" },
    { "value": 1997, "city": "湖南" },
    { "value": 5085, "city": "广东" },
    { "value": 1982, "city": "广西" },
    { "value": 3755, "city": "海南" },
    { "value": 1959, "city": "重庆" },
    { "value": 1854, "city": "四川" },
    { "value": 1234, "city": "贵州" },
    { "value": 2030, "city": "云南" },
    { "value": 1624, "city": "西藏" },
    { "value": 1981, "city": "陕西" },
    { "value": 1600, "city": "甘肃" },
    { "value": 2337, "city": "青海" },
    { "value": 2148, "city": "宁夏" },
    { "value": 2964, "city": "新疆" }
  ],
  "1994": [
    { "value": 3439, "city": "河北" },
    { "value": 10240, "city": "北京" },
    { "value": 7751, "city": "天津" },
    { "value": 2729, "city": "山西" },
    { "value": 3094, "city": "内蒙古" },
    { "value": 6103, "city": "辽宁" },
    { "value": 3657, "city": "吉林" },
    { "value": 4390, "city": "黑龙江" },
    { "value": 14328, "city": "上海" },
    { "value": 5801, "city": "江苏" },
    { "value": 6201, "city": "浙江" },
    { "value": 2257, "city": "安徽" },
    { "value": 5193, "city": "福建" },
    { "value": 2376, "city": "江西" },
    { "value": 4473, "city": "山东" },
    { "value": 2466.8, "city": "河南" },
    { "value": 2991.3, "city": "湖北" },
    { "value": 2630, "city": "湖南" },
    { "value": 6530, "city": "广东" },
    { "value": 2675, "city": "广西" },
    { "value": 4702.2, "city": "海南" },
    { "value": 2662, "city": "重庆" },
    { "value": 2338, "city": "四川" },
    { "value": 1527, "city": "贵州" },
    { "value": 2515, "city": "云南" },
    { "value": 1964, "city": "西藏" },
    { "value": 2424, "city": "陕西" },
    { "value": 1920.7, "city": "甘肃" },
    { "value": 2910, "city": "青海" },
    { "value": 2740, "city": "宁夏" },
    { "value": 3888, "city": "新疆" }
  ],
  "1995": [
    { "value": 4444, "city": "河北" },
    { "value": 12690, "city": "北京" },
    { "value": 9769, "city": "天津" },
    { "value": 3515, "city": "山西" },
    { "value": 3772, "city": "内蒙古" },
    { "value": 6880, "city": "辽宁" },
    { "value": 4402, "city": "吉林" },
    { "value": 5402, "city": "黑龙江" },
    { "value": 17779, "city": "上海" },
    { "value": 7319, "city": "江苏" },
    { "value": 8149, "city": "浙江" },
    { "value": 3070, "city": "安徽" },
    { "value": 6526, "city": "福建" },
    { "value": 2896, "city": "江西" },
    { "value": 5758, "city": "山东" },
    { "value": 3297.1, "city": "河南" },
    { "value": 3671.4, "city": "湖北" },
    { "value": 3359, "city": "湖南" },
    { "value": 8129, "city": "广东" },
    { "value": 3304, "city": "广西" },
    { "value": 5063.5, "city": "海南" },
    { "value": 3557, "city": "重庆" },
    { "value": 3043, "city": "四川" },
    { "value": 1826, "city": "贵州" },
    { "value": 3083, "city": "云南" },
    { "value": 2358, "city": "西藏" },
    { "value": 2965, "city": "陕西" },
    { "value": 2316.2, "city": "甘肃" },
    { "value": 3430, "city": "青海" },
    { "value": 3448, "city": "宁夏" },
    { "value": 4701, "city": "新疆" }
  ],
  "1996": [
    { "value": 5345, "city": "河北" },
    { "value": 14254, "city": "北京" },
    { "value": 11734, "city": "天津" },
    { "value": 4178, "city": "山西" },
    { "value": 4457, "city": "内蒙古" },
    { "value": 7730, "city": "辽宁" },
    { "value": 5178, "city": "吉林" },
    { "value": 6382, "city": "黑龙江" },
    { "value": 20647, "city": "上海" },
    { "value": 8471, "city": "江苏" },
    { "value": 9552, "city": "浙江" },
    { "value": 3524, "city": "安徽" },
    { "value": 7646, "city": "福建" },
    { "value": 3452, "city": "江西" },
    { "value": 6834, "city": "山东" },
    { "value": 3978.4, "city": "河南" },
    { "value": 4311, "city": "湖北" },
    { "value": 3963, "city": "湖南" },
    { "value": 9139, "city": "广东" },
    { "value": 3706, "city": "广西" },
    { "value": 5345.7, "city": "海南" },
    { "value": 4130, "city": "重庆" },
    { "value": 3550, "city": "四川" },
    { "value": 2048, "city": "贵州" },
    { "value": 3779, "city": "云南" },
    { "value": 2688, "city": "西藏" },
    { "value": 3446, "city": "陕西" },
    { "value": 2946.2, "city": "甘肃" },
    { "value": 3748, "city": "青海" },
    { "value": 3926, "city": "宁夏" },
    { "value": 5102, "city": "新疆" }
  ],
  "1997": [
    { "value": 6079, "city": "河北" },
    { "value": 16609, "city": "北京" },
    { "value": 13142, "city": "天津" },
    { "value": 4724, "city": "山西" },
    { "value": 4980, "city": "内蒙古" },
    { "value": 8725, "city": "辽宁" },
    { "value": 5591, "city": "吉林" },
    { "value": 7133, "city": "黑龙江" },
    { "value": 23397, "city": "上海" },
    { "value": 9371, "city": "江苏" },
    { "value": 10624, "city": "浙江" },
    { "value": 3929, "city": "安徽" },
    { "value": 8775, "city": "福建" },
    { "value": 3890, "city": "江西" },
    { "value": 7590, "city": "山东" },
    { "value": 4388.9, "city": "河南" },
    { "value": 4883.8, "city": "湖北" },
    { "value": 4420, "city": "湖南" },
    { "value": 10130, "city": "广东" },
    { "value": 3928, "city": "广西" },
    { "value": 5567, "city": "海南" },
    { "value": 4733, "city": "重庆" },
    { "value": 4032, "city": "四川" },
    { "value": 2250, "city": "贵州" },
    { "value": 4121, "city": "云南" },
    { "value": 3144, "city": "西藏" },
    { "value": 3834, "city": "陕西" },
    { "value": 3199.2, "city": "甘肃" },
    { "value": 4066, "city": "青海" },
    { "value": 4277, "city": "宁夏" },
    { "value": 5848, "city": "新疆" }
  ],
  "1998": [
    { "value": 6501, "city": "河北" },
    { "value": 19118, "city": "北京" },
    { "value": 14243, "city": "天津" },
    { "value": 5104, "city": "山西" },
    { "value": 5406, "city": "内蒙古" },
    { "value": 9415, "city": "辽宁" },
    { "value": 5983, "city": "吉林" },
    { "value": 7375, "city": "黑龙江" },
    { "value": 25206, "city": "上海" },
    { "value": 10049, "city": "江苏" },
    { "value": 11394, "city": "浙江" },
    { "value": 4235, "city": "安徽" },
    { "value": 9603, "city": "福建" },
    { "value": 4124, "city": "江西" },
    { "value": 8128, "city": "山东" },
    { "value": 4643, "city": "河南" },
    { "value": 5287, "city": "湖北" },
    { "value": 4667, "city": "湖南" },
    { "value": 10819, "city": "广东" },
    { "value": 4346, "city": "广西" },
    { "value": 5911.5, "city": "海南" },
    { "value": 5016, "city": "重庆" },
    { "value": 4294, "city": "四川" },
    { "value": 2364, "city": "贵州" },
    { "value": 4446, "city": "云南" },
    { "value": 3666, "city": "西藏" },
    { "value": 4070, "city": "陕西" },
    { "value": 3541.1, "city": "甘肃" },
    { "value": 4367, "city": "青海" },
    { "value": 4607, "city": "宁夏" },
    { "value": 6174, "city": "新疆" }
  ],
  "1999": [
    { "value": 6849, "city": "河北" },
    { "value": 21397, "city": "北京" },
    { "value": 15405, "city": "天津" },
    { "value": 5230, "city": "山西" },
    { "value": 5861, "city": "内蒙古" },
    { "value": 10086, "city": "辽宁" },
    { "value": 6382, "city": "吉林" },
    { "value": 7578, "city": "黑龙江" },
    { "value": 27071, "city": "上海" },
    { "value": 10695, "city": "江苏" },
    { "value": 12214, "city": "浙江" },
    { "value": 4495, "city": "安徽" },
    { "value": 10323, "city": "福建" },
    { "value": 4402, "city": "江西" },
    { "value": 8673, "city": "山东" },
    { "value": 4831.5, "city": "河南" },
    { "value": 5452.5, "city": "湖北" },
    { "value": 4933, "city": "湖南" },
    { "value": 11415, "city": "广东" },
    { "value": 4444, "city": "广西" },
    { "value": 6293.7, "city": "海南" },
    { "value": 5207, "city": "重庆" },
    { "value": 4540, "city": "四川" },
    { "value": 2545, "city": "贵州" },
    { "value": 4558, "city": "云南" },
    { "value": 4180, "city": "西藏" },
    { "value": 4415, "city": "陕西" },
    { "value": 3778.5, "city": "甘肃" },
    { "value": 4662, "city": "青海" },
    { "value": 4900, "city": "宁夏" },
    { "value": 6443, "city": "新疆" }
  ],
  "2000": [
    { "value": 7592, "city": "河北" },
    { "value": 24122, "city": "北京" },
    { "value": 17353, "city": "天津" },
    { "value": 5722, "city": "山西" },
    { "value": 6502, "city": "内蒙古" },
    { "value": 11177, "city": "辽宁" },
    { "value": 7351, "city": "吉林" },
    { "value": 8294, "city": "黑龙江" },
    { "value": 30047, "city": "上海" },
    { "value": 11765, "city": "江苏" },
    { "value": 13416, "city": "浙江" },
    { "value": 4779, "city": "安徽" },
    { "value": 11194, "city": "福建" },
    { "value": 4851, "city": "江西" },
    { "value": 9555, "city": "山东" },
    { "value": 5449.7, "city": "河南" },
    { "value": 6293.4, "city": "湖北" },
    { "value": 5425, "city": "湖南" },
    { "value": 12736, "city": "广东" },
    { "value": 4652, "city": "广西" },
    { "value": 6797.8, "city": "海南" },
    { "value": 5616, "city": "重庆" },
    { "value": 4956, "city": "四川" },
    { "value": 2759, "city": "贵州" },
    { "value": 4770, "city": "云南" },
    { "value": 4572, "city": "西藏" },
    { "value": 4968, "city": "陕西" },
    { "value": 4129.4, "city": "甘肃" },
    { "value": 5087, "city": "青海" },
    { "value": 5376, "city": "宁夏" },
    { "value": 7372, "city": "新疆" }
  ],
  "2001": [
    { "value": 8251, "city": "河北" },
    { "value": 26998, "city": "北京" },
    { "value": 19141, "city": "天津" },
    { "value": 6226, "city": "山西" },
    { "value": 7216, "city": "内蒙古" },
    { "value": 12015, "city": "辽宁" },
    { "value": 7893, "city": "吉林" },
    { "value": 8900, "city": "黑龙江" },
    { "value": 32333, "city": "上海" },
    { "value": 12882, "city": "江苏" },
    { "value": 14713, "city": "浙江" },
    { "value": 5313, "city": "安徽" },
    { "value": 11892, "city": "福建" },
    { "value": 5221, "city": "江西" },
    { "value": 10465, "city": "山东" },
    { "value": 5959.1, "city": "河南" },
    { "value": 6867, "city": "湖北" },
    { "value": 6120, "city": "湖南" },
    { "value": 13852, "city": "广东" },
    { "value": 5058, "city": "广西" },
    { "value": 7314.6, "city": "海南" },
    { "value": 6219, "city": "重庆" },
    { "value": 5376, "city": "四川" },
    { "value": 3000, "city": "贵州" },
    { "value": 5015, "city": "云南" },
    { "value": 5324, "city": "西藏" },
    { "value": 5506, "city": "陕西" },
    { "value": 4385.6, "city": "甘肃" },
    { "value": 5735, "city": "青海" },
    { "value": 6039, "city": "宁夏" },
    { "value": 7945, "city": "新疆" }
  ],
  "2002": [
    { "value": 8960, "city": "河北" },
    { "value": 30840, "city": "北京" },
    { "value": 21387, "city": "天津" },
    { "value": 7082, "city": "山西" },
    { "value": 8162, "city": "内蒙古" },
    { "value": 13000, "city": "辽宁" },
    { "value": 8714, "city": "吉林" },
    { "value": 9541, "city": "黑龙江" },
    { "value": 35445, "city": "上海" },
    { "value": 14396, "city": "江苏" },
    { "value": 16978, "city": "浙江" },
    { "value": 5736, "city": "安徽" },
    { "value": 12938, "city": "福建" },
    { "value": 5829, "city": "江西" },
    { "value": 11645, "city": "山东" },
    { "value": 6487, "city": "河南" },
    { "value": 7436.6, "city": "湖北" },
    { "value": 6734, "city": "湖南" },
    { "value": 15365, "city": "广东" },
    { "value": 5558, "city": "广西" },
    { "value": 8040.8, "city": "海南" },
    { "value": 7052, "city": "重庆" },
    { "value": 5890, "city": "四川" },
    { "value": 3257, "city": "贵州" },
    { "value": 5366, "city": "云南" },
    { "value": 6117, "city": "西藏" },
    { "value": 6145, "city": "陕西" },
    { "value": 4768.1, "city": "甘肃" },
    { "value": 6426, "city": "青海" },
    { "value": 6647, "city": "宁夏" },
    { "value": 8457, "city": "新疆" }
  ],
  "2003": [
    { "value": 10251, "city": "河北" },
    { "value": 34892, "city": "北京" },
    { "value": 25544, "city": "天津" },
    { "value": 8641, "city": "山西" },
    { "value": 10039, "city": "内蒙古" },
    { "value": 14270, "city": "辽宁" },
    { "value": 9854, "city": "吉林" },
    { "value": 10638, "city": "黑龙江" },
    { "value": 40130, "city": "上海" },
    { "value": 16830, "city": "江苏" },
    { "value": 20444, "city": "浙江" },
    { "value": 6375, "city": "安徽" },
    { "value": 14333, "city": "福建" },
    { "value": 6624, "city": "江西" },
    { "value": 13661, "city": "山东" },
    { "value": 7375.9, "city": "河南" },
    { "value": 8378, "city": "湖北" },
    { "value": 7589, "city": "湖南" },
    { "value": 17798, "city": "广东" },
    { "value": 6169, "city": "广西" },
    { "value": 8849, "city": "海南" },
    { "value": 8091, "city": "重庆" },
    { "value": 6623, "city": "四川" },
    { "value": 3701, "city": "贵州" },
    { "value": 5870, "city": "云南" },
    { "value": 6893, "city": "西藏" },
    { "value": 7028, "city": "陕西" },
    { "value": 5429.4, "city": "甘肃" },
    { "value": 7277, "city": "青海" },
    { "value": 7734, "city": "宁夏" },
    { "value": 9828, "city": "新疆" }
  ],
  "2004": [
    { "value": 12487, "city": "河北" },
    { "value": 41099, "city": "北京" },
    { "value": 30575, "city": "天津" },
    { "value": 10741, "city": "山西" },
    { "value": 12767, "city": "内蒙古" },
    { "value": 15835, "city": "辽宁" },
    { "value": 11537, "city": "吉林" },
    { "value": 12449, "city": "黑龙江" },
    { "value": 46755, "city": "上海" },
    { "value": 20223, "city": "江苏" },
    { "value": 24352, "city": "浙江" },
    { "value": 7681, "city": "安徽" },
    { "value": 16469, "city": "福建" },
    { "value": 8097, "city": "江西" },
    { "value": 16925, "city": "山东" },
    { "value": 9200.6, "city": "河南" },
    { "value": 9897.6, "city": "湖北" },
    { "value": 9165, "city": "湖南" },
    { "value": 20876, "city": "广东" },
    { "value": 7461, "city": "广西" },
    { "value": 10067.4, "city": "海南" },
    { "value": 9624, "city": "重庆" },
    { "value": 7895, "city": "四川" },
    { "value": 4317, "city": "贵州" },
    { "value": 7012, "city": "云南" },
    { "value": 8103, "city": "西藏" },
    { "value": 8587, "city": "陕西" },
    { "value": 6566.1, "city": "甘肃" },
    { "value": 8606, "city": "青海" },
    { "value": 9199, "city": "宁夏" },
    { "value": 11337, "city": "新疆" }
  ],
  "2005": [
    { "value": 14782, "city": "河北" },
    { "value": 45444, "city": "北京" },
    { "value": 35783, "city": "天津" },
    { "value": 12495, "city": "山西" },
    { "value": 16331, "city": "内蒙古" },
    { "value": 18983, "city": "辽宁" },
    { "value": 13348, "city": "吉林" },
    { "value": 14434, "city": "黑龙江" },
    { "value": 52060, "city": "上海" },
    { "value": 24560, "city": "江苏" },
    { "value": 27703, "city": "浙江" },
    { "value": 8670, "city": "安徽" },
    { "value": 18646, "city": "福建" },
    { "value": 9440, "city": "江西" },
    { "value": 20096, "city": "山东" },
    { "value": 11346.5, "city": "河南" },
    { "value": 11431, "city": "湖北" },
    { "value": 10426, "city": "湖南" },
    { "value": 24438, "city": "广东" },
    { "value": 8788, "city": "广西" },
    { "value": 10997.9, "city": "海南" },
    { "value": 10982, "city": "重庆" },
    { "value": 9060, "city": "四川" },
    { "value": 5052, "city": "贵州" },
    { "value": 7835, "city": "云南" },
    { "value": 9114, "city": "西藏" },
    { "value": 10161, "city": "陕西" },
    { "value": 7476.5, "city": "甘肃" },
    { "value": 10045, "city": "青海" },
    { "value": 10239, "city": "宁夏" },
    { "value": 13108, "city": "新疆" }
  ],
  "2006": [
    { "value": 16752, "city": "河北" },
    { "value": 50407, "city": "北京" },
    { "value": 41022, "city": "天津" },
    { "value": 14011, "city": "山西" },
    { "value": 20264, "city": "内蒙古" },
    { "value": 21788, "city": "辽宁" },
    { "value": 15720, "city": "吉林" },
    { "value": 16228, "city": "黑龙江" },
    { "value": 57695, "city": "上海" },
    { "value": 28814, "city": "江苏" },
    { "value": 31874, "city": "浙江" },
    { "value": 10026, "city": "安徽" },
    { "value": 21385, "city": "福建" },
    { "value": 10798, "city": "江西" },
    { "value": 23794, "city": "山东" },
    { "value": 13172, "city": "河南" },
    { "value": 13296, "city": "湖北" },
    { "value": 11950, "city": "湖南" },
    { "value": 28284, "city": "广东" },
    { "value": 10296, "city": "广西" },
    { "value": 12403, "city": "海南" },
    { "value": 12316, "city": "重庆" },
    { "value": 10546, "city": "四川" },
    { "value": 5759, "city": "贵州" },
    { "value": 8970, "city": "云南" },
    { "value": 10430, "city": "西藏" },
    { "value": 12138, "city": "陕西" },
    { "value": 8757, "city": "甘肃" },
    { "value": 11724, "city": "青海" },
    { "value": 11847, "city": "宁夏" },
    { "value": 15000, "city": "新疆" }
  ],
  "2007": [
    { "value": 19877, "city": "河北" },
    { "value": 58204, "city": "北京" },
    { "value": 46122, "city": "天津" },
    { "value": 16945, "city": "山西" },
    { "value": 25393, "city": "内蒙古" },
    { "value": 25729, "city": "辽宁" },
    { "value": 19383, "city": "吉林" },
    { "value": 18478, "city": "黑龙江" },
    { "value": 66367, "city": "上海" },
    { "value": 33928, "city": "江苏" },
    { "value": 37411, "city": "浙江" },
    { "value": 12045, "city": "安徽" },
    { "value": 25908, "city": "福建" },
    { "value": 12633, "city": "江西" },
    { "value": 27807, "city": "山东" },
    { "value": 16012, "city": "河南" },
    { "value": 16206, "city": "湖北" },
    { "value": 14492, "city": "湖南" },
    { "value": 33151, "city": "广东" },
    { "value": 12555, "city": "广西" },
    { "value": 14555, "city": "海南" },
    { "value": 14660, "city": "重庆" },
    { "value": 12893, "city": "四川" },
    { "value": 6915, "city": "贵州" },
    { "value": 10540, "city": "云南" },
    { "value": 12109, "city": "西藏" },
    { "value": 14607, "city": "陕西" },
    { "value": 10346, "city": "甘肃" },
    { "value": 14257, "city": "青海" },
    { "value": 14649, "city": "宁夏" },
    { "value": 16950, "city": "新疆" }
  ],
  "2008": [
    { "value": 22986, "city": "河北" },
    { "value": 64491, "city": "北京" },
    { "value": 58656, "city": "天津" },
    { "value": 21506, "city": "山西" },
    { "value": 34869, "city": "内蒙古" },
    { "value": 31739, "city": "辽宁" },
    { "value": 23521, "city": "吉林" },
    { "value": 21740, "city": "黑龙江" },
    { "value": 66932, "city": "上海" },
    { "value": 40014, "city": "江苏" },
    { "value": 41405, "city": "浙江" },
    { "value": 14448, "city": "安徽" },
    { "value": 29755, "city": "福建" },
    { "value": 15900, "city": "江西" },
    { "value": 32936, "city": "山东" },
    { "value": 19181, "city": "河南" },
    { "value": 19858, "city": "湖北" },
    { "value": 18147, "city": "湖南" },
    { "value": 37638, "city": "广东" },
    { "value": 14652, "city": "广西" },
    { "value": 17691, "city": "海南" },
    { "value": 20490, "city": "重庆" },
    { "value": 15495, "city": "四川" },
    { "value": 9855, "city": "贵州" },
    { "value": 12570, "city": "云南" },
    { "value": 13588, "city": "西藏" },
    { "value": 19700, "city": "陕西" },
    { "value": 12421, "city": "甘肃" },
    { "value": 18421, "city": "青海" },
    { "value": 19609, "city": "宁夏" },
    { "value": 19797, "city": "新疆" }
  ],
  "2009": [
    { "value": 24581, "city": "河北" },
    { "value": 66940, "city": "北京" },
    { "value": 62574, "city": "天津" },
    { "value": 21522, "city": "山西" },
    { "value": 39735, "city": "内蒙古" },
    { "value": 35149, "city": "辽宁" },
    { "value": 26595, "city": "吉林" },
    { "value": 22447, "city": "黑龙江" },
    { "value": 69165, "city": "上海" },
    { "value": 44253, "city": "江苏" },
    { "value": 43842, "city": "浙江" },
    { "value": 16408, "city": "安徽" },
    { "value": 33437, "city": "福建" },
    { "value": 17335, "city": "江西" },
    { "value": 35894, "city": "山东" },
    { "value": 20597, "city": "河南" },
    { "value": 22677, "city": "湖北" },
    { "value": 20428, "city": "湖南" },
    { "value": 39436, "city": "广东" },
    { "value": 16045, "city": "广西" },
    { "value": 19254, "city": "海南" },
    { "value": 22920, "city": "重庆" },
    { "value": 17339, "city": "四川" },
    { "value": 10971, "city": "贵州" },
    { "value": 13539, "city": "云南" },
    { "value": 15008, "city": "西藏" },
    { "value": 21947, "city": "陕西" },
    { "value": 13269, "city": "甘肃" },
    { "value": 19454, "city": "青海" },
    { "value": 21777, "city": "宁夏" },
    { "value": 19942, "city": "新疆" }
  ],
  "2010": [
    { "value": 28668, "city": "河北" },
    { "value": 73856, "city": "北京" },
    { "value": 72994, "city": "天津" },
    { "value": 26283, "city": "山西" },
    { "value": 47347, "city": "内蒙古" },
    { "value": 42355, "city": "辽宁" },
    { "value": 31599, "city": "吉林" },
    { "value": 27076, "city": "黑龙江" },
    { "value": 76074, "city": "上海" },
    { "value": 52840, "city": "江苏" },
    { "value": 51711, "city": "浙江" },
    { "value": 20888, "city": "安徽" },
    { "value": 40025, "city": "福建" },
    { "value": 21253, "city": "江西" },
    { "value": 41106, "city": "山东" },
    { "value": 24446, "city": "河南" },
    { "value": 27906, "city": "湖北" },
    { "value": 24719, "city": "湖南" },
    { "value": 44736, "city": "广东" },
    { "value": 20219, "city": "广西" },
    { "value": 23831, "city": "海南" },
    { "value": 27596, "city": "重庆" },
    { "value": 21182, "city": "四川" },
    { "value": 13119, "city": "贵州" },
    { "value": 15752, "city": "云南" },
    { "value": 17027, "city": "西藏" },
    { "value": 27133, "city": "陕西" },
    { "value": 16113, "city": "甘肃" },
    { "value": 24115, "city": "青海" },
    { "value": 26860, "city": "宁夏" },
    { "value": 25034, "city": "新疆" }
  ],
  "2011": [
    { "value": 33969, "city": "河北" },
    { "value": 81658, "city": "北京" },
    { "value": 85213, "city": "天津" },
    { "value": 31357, "city": "山西" },
    { "value": 57974, "city": "内蒙古" },
    { "value": 50760, "city": "辽宁" },
    { "value": 38460, "city": "吉林" },
    { "value": 32819, "city": "黑龙江" },
    { "value": 82560, "city": "上海" },
    { "value": 62290, "city": "江苏" },
    { "value": 59249, "city": "浙江" },
    { "value": 25659, "city": "安徽" },
    { "value": 47377, "city": "福建" },
    { "value": 26150, "city": "江西" },
    { "value": 47335, "city": "山东" },
    { "value": 28661, "city": "河南" },
    { "value": 34197, "city": "湖北" },
    { "value": 29880, "city": "湖南" },
    { "value": 50807, "city": "广东" },
    { "value": 25326, "city": "广西" },
    { "value": 28898, "city": "海南" },
    { "value": 34500, "city": "重庆" },
    { "value": 26133, "city": "四川" },
    { "value": 16413, "city": "贵州" },
    { "value": 19265, "city": "云南" },
    { "value": 20077, "city": "西藏" },
    { "value": 33464, "city": "陕西" },
    { "value": 19595, "city": "甘肃" },
    { "value": 29522, "city": "青海" },
    { "value": 33043, "city": "宁夏" },
    { "value": 30087, "city": "新疆" }
  ],
  "2012": [
    { "value": 36584, "city": "河北" },
    { "value": 87475, "city": "北京" },
    { "value": 93173, "city": "天津" },
    { "value": 33628, "city": "山西" },
    { "value": 63886, "city": "内蒙古" },
    { "value": 56649, "city": "辽宁" },
    { "value": 43415, "city": "吉林" },
    { "value": 35711, "city": "黑龙江" },
    { "value": 85373, "city": "上海" },
    { "value": 68347, "city": "江苏" },
    { "value": 63374, "city": "浙江" },
    { "value": 28792, "city": "安徽" },
    { "value": 52763, "city": "福建" },
    { "value": 28800, "city": "江西" },
    { "value": 51768, "city": "山东" },
    { "value": 31499, "city": "河南" },
    { "value": 38572, "city": "湖北" },
    { "value": 33480, "city": "湖南" },
    { "value": 54095, "city": "广东" },
    { "value": 27952, "city": "广西" },
    { "value": 32377, "city": "海南" },
    { "value": 38914, "city": "重庆" },
    { "value": 29608, "city": "四川" },
    { "value": 19710, "city": "贵州" },
    { "value": 22195, "city": "云南" },
    { "value": 22936, "city": "西藏" },
    { "value": 38564, "city": "陕西" },
    { "value": 21978, "city": "甘肃" },
    { "value": 33181, "city": "青海" },
    { "value": 36394, "city": "宁夏" },
    { "value": 33796, "city": "新疆" }
  ],
  "2013": [
    { "value": 38909, "city": "河北" },
    { "value": 94648, "city": "北京" },
    { "value": 100105, "city": "天津" },
    { "value": 34984, "city": "山西" },
    { "value": 67836, "city": "内蒙古" },
    { "value": 61996, "city": "辽宁" },
    { "value": 47428, "city": "吉林" },
    { "value": 37697, "city": "黑龙江" },
    { "value": 90993, "city": "上海" },
    { "value": 75354, "city": "江苏" },
    { "value": 68805, "city": "浙江" },
    { "value": 32001, "city": "安徽" },
    { "value": 58145, "city": "福建" },
    { "value": 31930, "city": "江西" },
    { "value": 56885, "city": "山东" },
    { "value": 34211, "city": "河南" },
    { "value": 42826, "city": "湖北" },
    { "value": 36943, "city": "湖南" },
    { "value": 58833, "city": "广东" },
    { "value": 30741, "city": "广西" },
    { "value": 35663, "city": "海南" },
    { "value": 43223, "city": "重庆" },
    { "value": 32617, "city": "四川" },
    { "value": 23151, "city": "贵州" },
    { "value": 25322, "city": "云南" },
    { "value": 26326, "city": "西藏" },
    { "value": 43117, "city": "陕西" },
    { "value": 24539, "city": "甘肃" },
    { "value": 36875, "city": "青海" },
    { "value": 39613, "city": "宁夏" },
    { "value": 37553, "city": "新疆" }
  ],
  "2014": [
    { "value": 39984, "city": "河北" },
    { "value": 99995, "city": "北京" },
    { "value": 105231, "city": "天津" },
    { "value": 35070, "city": "山西" },
    { "value": 71046, "city": "内蒙古" },
    { "value": 65201, "city": "辽宁" },
    { "value": 50160, "city": "吉林" },
    { "value": 39226, "city": "黑龙江" },
    { "value": 97370, "city": "上海" },
    { "value": 81874, "city": "江苏" },
    { "value": 73002, "city": "浙江" },
    { "value": 34425, "city": "安徽" },
    { "value": 63472, "city": "福建" },
    { "value": 34674, "city": "江西" },
    { "value": 60879, "city": "山东" },
    { "value": 37072, "city": "河南" },
    { "value": 47145, "city": "湖北" },
    { "value": 40271, "city": "湖南" },
    { "value": 63469, "city": "广东" },
    { "value": 33090, "city": "广西" },
    { "value": 38924, "city": "海南" },
    { "value": 47850, "city": "重庆" },
    { "value": 35128, "city": "四川" },
    { "value": 26437, "city": "贵州" },
    { "value": 27264, "city": "云南" },
    { "value": 29252, "city": "西藏" },
    { "value": 46929, "city": "陕西" },
    { "value": 26433, "city": "甘肃" },
    { "value": 39671, "city": "青海" },
    { "value": 41834, "city": "宁夏" },
    { "value": 40648, "city": "新疆" }
  ],
  "2015": [
    { "value": 40255, "city": "河北" },
    { "value": 106497, "city": "北京" },
    { "value": 107960, "city": "天津" },
    { "value": 34919, "city": "山西" },
    { "value": 71101, "city": "内蒙古" },
    { "value": 65354, "city": "辽宁" },
    { "value": 51086, "city": "吉林" },
    { "value": 39462, "city": "黑龙江" },
    { "value": 103796, "city": "上海" },
    { "value": 87995, "city": "江苏" },
    { "value": 77644, "city": "浙江" },
    { "value": 35997, "city": "安徽" },
    { "value": 67966, "city": "福建" },
    { "value": 36724, "city": "江西" },
    { "value": 64168, "city": "山东" },
    { "value": 39123, "city": "河南" },
    { "value": 50654, "city": "湖北" },
    { "value": 42754, "city": "湖南" },
    { "value": 67503, "city": "广东" },
    { "value": 35190, "city": "广西" },
    { "value": 40818, "city": "海南" },
    { "value": 52321, "city": "重庆" },
    { "value": 36775, "city": "四川" },
    { "value": 29847, "city": "贵州" },
    { "value": 28806, "city": "云南" },
    { "value": 31999, "city": "西藏" },
    { "value": 47626, "city": "陕西" },
    { "value": 26165, "city": "甘肃" },
    { "value": 41252, "city": "青海" },
    { "value": 43805, "city": "宁夏" },
    { "value": 40036, "city": "新疆" }
  ],
  "2016": [
    { "value": 43062, "city": "河北" },
    { "value": 118198, "city": "北京" },
    { "value": 115053, "city": "天津" },
    { "value": 35532, "city": "山西" },
    { "value": 72064, "city": "内蒙古" },
    { "value": 50791, "city": "辽宁" },
    { "value": 53868, "city": "吉林" },
    { "value": 40432, "city": "黑龙江" },
    { "value": 116562, "city": "上海" },
    { "value": 96887, "city": "江苏" },
    { "value": 84916, "city": "浙江" },
    { "value": 39561, "city": "安徽" },
    { "value": 74707, "city": "福建" },
    { "value": 40400, "city": "江西" },
    { "value": 68733, "city": "山东" },
    { "value": 42575, "city": "河南" },
    { "value": 55665, "city": "湖北" },
    { "value": 46382, "city": "湖南" },
    { "value": 74016, "city": "广东" },
    { "value": 38027, "city": "广西" },
    { "value": 44347, "city": "海南" },
    { "value": 58502, "city": "重庆" },
    { "value": 40003, "city": "四川" },
    { "value": 33246, "city": "贵州" },
    { "value": 31093, "city": "云南" },
    { "value": 35184, "city": "西藏" },
    { "value": 51015, "city": "陕西" },
    { "value": 27643, "city": "甘肃" },
    { "value": 43531, "city": "青海" },
    { "value": 47194, "city": "宁夏" },
    { "value": 40564, "city": "新疆" }
  ],
  "2017": [
    { "value": 45387, "city": "河北" },
    { "value": 128994, "city": "北京" },
    { "value": 118944, "city": "天津" },
    { "value": 42060, "city": "山西" },
    { "value": 63764, "city": "内蒙古" },
    { "value": 53527, "city": "辽宁" },
    { "value": 54838, "city": "吉林" },
    { "value": 41916, "city": "黑龙江" },
    { "value": 126634, "city": "上海" },
    { "value": 107150, "city": "江苏" },
    { "value": 92057, "city": "浙江" },
    { "value": 43401, "city": "安徽" },
    { "value": 82677, "city": "福建" },
    { "value": 43424, "city": "江西" },
    { "value": 72807, "city": "山东" },
    { "value": 46674, "city": "河南" },
    { "value": 60199, "city": "湖北" },
    { "value": 49558, "city": "湖南" },
    { "value": 80932, "city": "广东" },
    { "value": 38102, "city": "广西" },
    { "value": 48430, "city": "海南" },
    { "value": 63442, "city": "重庆" },
    { "value": 44651, "city": "四川" },
    { "value": 37956, "city": "贵州" },
    { "value": 34221, "city": "云南" },
    { "value": 39267, "city": "西藏" },
    { "value": 57266, "city": "陕西" },
    { "value": 28497, "city": "甘肃" },
    { "value": 44047, "city": "青海" },
    { "value": 50765, "city": "宁夏" },
    { "value": 44941, "city": "新疆" }
  ]
}
